env/bin/rst2html.py
env/bin/rst2html4.py
env/bin/rst2html5.py
env/bin/rst2latex.py
env/bin/rst2man.py
env/bin/rst2odt.py
env/bin/rst2odt_prepstyles.py
env/bin/rst2pseudoxml.py
env/bin/rst2s5.py
env/bin/rst2xetex.py
env/bin/rst2xml.py
env/bin/rstpep2html.py
progressbar/__about__.py
progressbar/__init__.py
progressbar/bar.py
progressbar/base.py
progressbar/converters.py
progressbar/env.py
progressbar/multi.py
progressbar/py.typed
progressbar/shortcuts.py
progressbar/utils.py
progressbar/widgets.py
progressbar/terminal/__init__.py
progressbar/terminal/base.py
progressbar/terminal/colors.py
progressbar/terminal/size.py
progressbar/terminal/stream.py
progressbar/terminal/os_specific/__init__.py
progressbar/terminal/os_specific/posix.py
progressbar/terminal/os_specific/windows.py
progressbar3-4.3.4.dist-info/LICENSE
progressbar3-4.3.4.dist-info/METADATA
progressbar3-4.3.4.dist-info/WHEEL
progressbar3-4.3.4.dist-info/top_level.txt
progressbar3-4.3.4.dist-info/RECORD
