Metadata-Version: 2.1
Name: progressbar3
Version: 4.3.4
Summary: A Python Progressbar library to provide visual (yet text based) progress to long running operations.
Author-email: "Rick van Hattem (Wolph)" <wolph@wol.ph>
License: BSD-3-Clause
Project-URL: bugs, https://github.com/wolph/python-progressbar/issues
Project-URL: documentation, https://progressbar-2.readthedocs.io/en/latest/
Project-URL: repository, https://github.com/wolph/python-progressbar/
Keywords: REPL,animated,bar,color,console,duration,efficient,elapsed,eta,feedback,live,meter,monitor,monitoring,multi-threaded,progress,progress-bar,progressbar,progressmeter,python,rate,simple,speed,spinner,stats,terminal,throughput,time,visual
Platform: UNKNOWN
Classifier: Development Status :: 5 - Production/Stable
Classifier: Development Status :: 6 - Mature
Classifier: Environment :: Console
Classifier: Environment :: MacOS X
Classifier: Environment :: Other Environment
Classifier: Environment :: Win32 (MS Windows)
Classifier: Environment :: X11 Applications
Classifier: Framework :: IPython
Classifier: Framework :: Jupyter
Classifier: Intended Audience :: Developers
Classifier: Intended Audience :: Education
Classifier: Intended Audience :: End Users/Desktop
Classifier: Intended Audience :: Other Audience
Classifier: Intended Audience :: System Administrators
Classifier: License :: OSI Approved :: BSD License
Classifier: Natural Language :: English
Classifier: Operating System :: MacOS :: MacOS X
Classifier: Operating System :: MacOS
Classifier: Operating System :: Microsoft :: MS-DOS
Classifier: Operating System :: Microsoft :: Windows
Classifier: Operating System :: Microsoft
Classifier: Operating System :: POSIX :: BSD :: FreeBSD
Classifier: Operating System :: POSIX :: BSD
Classifier: Operating System :: POSIX :: Linux
Classifier: Operating System :: POSIX :: SunOS/Solaris
Classifier: Operating System :: POSIX
Classifier: Operating System :: Unix
Classifier: Programming Language :: Python :: 3 :: Only
Classifier: Programming Language :: Python :: 3
Classifier: Programming Language :: Python :: 3.10
Classifier: Programming Language :: Python :: 3.11
Classifier: Programming Language :: Python :: 3.12
Classifier: Programming Language :: Python :: 3.8
Classifier: Programming Language :: Python :: 3.9
Classifier: Programming Language :: Python :: Implementation :: IronPython
Classifier: Programming Language :: Python :: Implementation :: PyPy
Classifier: Programming Language :: Python :: Implementation
Classifier: Programming Language :: Python
Classifier: Programming Language :: Unix Shell
Classifier: Topic :: Desktop Environment
Classifier: Topic :: Education :: Computer Aided Instruction (CAI)
Classifier: Topic :: Education :: Testing
Classifier: Topic :: Office/Business
Classifier: Topic :: Other/Nonlisted Topic
Classifier: Topic :: Software Development :: Build Tools
Classifier: Topic :: Software Development :: Libraries :: Python Modules
Classifier: Topic :: Software Development :: Libraries
Classifier: Topic :: Software Development :: Pre-processors
Classifier: Topic :: Software Development :: User Interfaces
Classifier: Topic :: System :: Installation/Setup
Classifier: Topic :: System :: Logging
Classifier: Topic :: System :: Monitoring
Classifier: Topic :: System :: Shells
Classifier: Topic :: Terminals
Classifier: Topic :: Utilities
Requires-Python: >=3.11
License-File: LICENSE
Provides-Extra: docs
Requires-Dist: sphinx >=1.8.5 ; extra == 'docs'
Requires-Dist: sphinx-autodoc-typehints >=1.6.0 ; extra == 'docs'
Provides-Extra: tests
Requires-Dist: dill >=0.3.6 ; extra == 'tests'
Requires-Dist: flake8 >=3.7.7 ; extra == 'tests'
Requires-Dist: freezegun >=0.3.11 ; extra == 'tests'
Requires-Dist: pytest-cov >=2.6.1 ; extra == 'tests'
Requires-Dist: pytest-mypy ; extra == 'tests'
Requires-Dist: pytest >=4.6.9 ; extra == 'tests'
Requires-Dist: sphinx >=1.8.5 ; extra == 'tests'
